big_data_normality/__init__.py
big_data_normality/empirical_normality_test.py
big_data_normality/emprical_normality_test_graph.py
big_data_normality-0.1.6.dist-info/METADATA
big_data_normality-0.1.6.dist-info/WHEEL
big_data_normality-0.1.6.dist-info/top_level.txt
big_data_normality-0.1.6.dist-info/RECORD
