Metadata-Version: 2.1
Name: big-data-normality
Version: 0.1.6
Summary: Normality Test for Big Data
Home-page: https://github.com/serhateerdem
Author: Serhat Erdem
Author-email: erdemserhat1994@gmail.com
Classifier: Programming Language :: Python :: 3.9
Requires-Python: >=3.9
Requires-Dist: numpy (>=1.22.3)
Requires-Dist: pandas (>=1.4.2)
Requires-Dist: scipy (>=1.8.0)
Requires-Dist: statistics (>=1.0.3.5)
